Metadata-Version: 2.1
Name: iosolver
Version: 0.1
Summary: A package used for io operations
Home-page: https://github.com/jackl001/iosolver
Author: jackl001
Author-email: caozhankui@outlook.com
License: MIT
Platform: UNKNOWN
Classifier: Programming Language :: Python :: 3
Classifier: License :: OSI Approved :: MIT License
Classifier: Operating System :: OS Independent
Requires-Python: >=3.6
